pytorch_segmentation_models_trainer/__init__.py
pytorch_segmentation_models_trainer/build_mask.py
pytorch_segmentation_models_trainer/config.py
pytorch_segmentation_models_trainer/config_utils.py
pytorch_segmentation_models_trainer/convert_ds.py
pytorch_segmentation_models_trainer/evaluate_experiments.py
pytorch_segmentation_models_trainer/main.py
pytorch_segmentation_models_trainer/predict.py
pytorch_segmentation_models_trainer/predict_from_batch.py
pytorch_segmentation_models_trainer/predict_mod_polymapper_from_batch.py
pytorch_segmentation_models_trainer/server.py
pytorch_segmentation_models_trainer/train.py
pytorch_segmentation_models_trainer/validate_evaluation_config.py
pytorch_segmentation_models_trainer/conf/__init__.py
pytorch_segmentation_models_trainer/config_definitions/__init__.py
pytorch_segmentation_models_trainer/config_definitions/coco_dataset_config.py
pytorch_segmentation_models_trainer/config_definitions/dataset_config.py
pytorch_segmentation_models_trainer/config_definitions/evaluation_config.py
pytorch_segmentation_models_trainer/config_definitions/inference_config.py
pytorch_segmentation_models_trainer/config_definitions/loss_config_definition.py
pytorch_segmentation_models_trainer/config_definitions/predict_config.py
pytorch_segmentation_models_trainer/config_definitions/tools_config_def.py
pytorch_segmentation_models_trainer/config_definitions/train_config.py
pytorch_segmentation_models_trainer/custom_callbacks/__init__.py
pytorch_segmentation_models_trainer/custom_callbacks/image_callbacks.py
pytorch_segmentation_models_trainer/custom_callbacks/metrics_callbacks.py
pytorch_segmentation_models_trainer/custom_callbacks/training_callbacks.py
pytorch_segmentation_models_trainer/custom_losses/__init__.py
pytorch_segmentation_models_trainer/custom_losses/base_loss.py
pytorch_segmentation_models_trainer/custom_losses/crossfield_losses.py
pytorch_segmentation_models_trainer/custom_losses/loss.py
pytorch_segmentation_models_trainer-1.0.0.dist-info/licenses/LICENSE
pytorch_segmentation_models_trainer-1.0.0.dist-info/METADATA
pytorch_segmentation_models_trainer-1.0.0.dist-info/WHEEL
pytorch_segmentation_models_trainer-1.0.0.dist-info/entry_points.txt
pytorch_segmentation_models_trainer-1.0.0.dist-info/top_level.txt
pytorch_segmentation_models_trainer-1.0.0.dist-info/RECORD
