Metadata-Version: 2.4
Name: pytorch_segmentation_models_trainer
Version: 1.0.0
Summary: Image segmentation models training of popular architectures.
Home-page: https://github.com/phborba/pytorch_segmentation_models_trainer
Author: Philipe Borba
Author-email: philipeborba@gmail.com
License: GPL
Keywords: pytorch hydra semantic-segmentation deep-learning deep learning
Classifier: Development Status :: 4 - Beta
Classifier: Intended Audience :: Developers
Classifier: Operating System :: OS Independent
Classifier: Topic :: Software Development :: Libraries :: Python Modules
Classifier: License :: OSI Approved :: GNU General Public License v2 (GPLv2)
Classifier: Programming Language :: Python
Classifier: Programming Language :: Python :: 3
Classifier: Programming Language :: Python :: Implementation :: CPython
Classifier: Programming Language :: Python :: Implementation :: PyPy
Requires-Python: >=3.6.0
License-File: LICENSE
Provides-Extra: tests
Requires-Dist: pytest; extra == "tests"
Requires-Dist: scikit-image; extra == "tests"
Requires-Dist: parameterized; extra == "tests"
Dynamic: author
Dynamic: author-email
Dynamic: classifier
Dynamic: description
Dynamic: description-content-type
Dynamic: home-page
Dynamic: keywords
Dynamic: license
Dynamic: license-file
Dynamic: provides-extra
Dynamic: requires-python
Dynamic: summary
